LICENSE
LICENSE.unhosted
MANIFEST.in
README.txt
setup.py
django_remotestorage/__init__.py
django_remotestorage/admin.py
django_remotestorage/models.py
django_remotestorage/settings_base.py
django_remotestorage/tests.py
django_remotestorage/urls.py
django_remotestorage/utils.py
django_remotestorage/views.py
django_remotestorage.egg-info/PKG-INFO
django_remotestorage.egg-info/SOURCES.txt
django_remotestorage.egg-info/dependency_links.txt
django_remotestorage.egg-info/not-zip-safe
django_remotestorage.egg-info/requires.txt
django_remotestorage.egg-info/top_level.txt
django_remotestorage/apps/__init__.py
django_remotestorage/apps/account/__init__.py
django_remotestorage/apps/account/forms.py
django_remotestorage/apps/account/urls.py
django_remotestorage/apps/account/views.py
django_remotestorage/apps/api/__init__.py
django_remotestorage/apps/api/models.py
django_remotestorage/apps/api/urls.py
django_remotestorage/apps/api/views.py
django_remotestorage/apps/demo/__init__.py
django_remotestorage/apps/demo/urls.py
django_remotestorage/apps/demo/views.py
django_remotestorage/apps/oauth2/__init__.py
django_remotestorage/apps/oauth2/forms.py
django_remotestorage/apps/oauth2/urls.py
django_remotestorage/apps/oauth2/views.py
django_remotestorage/apps/webfinger/__init__.py
django_remotestorage/apps/webfinger/urls.py
django_remotestorage/apps/webfinger/views.py
django_remotestorage/apps/webfinger/xrd.py
django_remotestorage/apps/webfinger/xrd_gen.py
django_remotestorage/management/__init__.py
django_remotestorage/management/commands/__init__.py
django_remotestorage/management/commands/access_token_cleanup.py
django_remotestorage/migrations/0001_initial.py
django_remotestorage/migrations/0002_auto__add_storedobject__add_unique_storedobject_user_path.py
django_remotestorage/migrations/__init__.py
django_remotestorage/static/django_remotestorage_client/app.js
django_remotestorage/static/django_remotestorage_client/helper.js
django_remotestorage/static/django_remotestorage_client/token.js
django_remotestorage/static/django_remotestorage_client/tutorial.js
django_remotestorage/templates/layout.html
django_remotestorage/templates/message_box.html
django_remotestorage/templates/account/clients.html
